llama_index/output_parsers/guardrails/__init__.py
llama_index/output_parsers/guardrails/base.py
llama_index_output_parsers_guardrails-0.4.1.dist-info/METADATA
llama_index_output_parsers_guardrails-0.4.1.dist-info/WHEEL
llama_index_output_parsers_guardrails-0.4.1.dist-info/licenses/LICENSE
llama_index_output_parsers_guardrails-0.4.1.dist-info/RECORD
