Metadata-Version: 2.4
Name: llama-index-output-parsers-guardrails
Version: 0.4.1
Summary: llama-index output_parsers guardrails integration
Author-email: Your Name <you@example.com>
License-Expression: MIT
License-File: LICENSE
Requires-Python: <4.0,>=3.9
Requires-Dist: guardrails-ai<0.5,>=0.4.1
Requires-Dist: llama-index-core<0.15,>=0.13.0
